{
  "name": "mitigation_cb2024-400mt-hires",
  "data": [
    {
      "seriesName": "SEAI_BIOENERGY",
      "seriesValues": [
        [
          2018,
          18.0418703064732
        ],
        [
          2019,
          18.456875923801356
        ],
        [
          2020,
          17.577286198834404
        ],
        [
          2021,
          17.923834063343357
        ],
        [
          2022,
          20.18373793194373
        ],
        [
          2023,
          23.622000577113152
        ],
        [
          2024,
          29.343615373651502
        ],
        [
          2025,
          30.194588685469018
        ],
        [
          2026,
          38.41945560672082
        ],
        [
          2027,
          43.03682126286443
        ],
        [
          2028,
          46.932272090933715
        ],
        [
          2029,
          48.801303589522206
        ],
        [
          2030,
          50.24490130622394
        ],
        [
          2031,
          43.04051735498214
        ],
        [
          2032,
          43.92044649726005
        ],
        [
          2033,
          45.077333487079684
        ],
        [
          2034,
          43.06852590211209
        ],
        [
          2035,
          42.00622104473397
        ],
        [
          2036,
          43.17164312853857
        ],
        [
          2037,
          43.78121274753335
        ],
        [
          2038,
          43.47347137496763
        ],
        [
          2039,
          44.28849279524326
        ],
        [
          2040,
          45.216647220177144
        ],
        [
          2041,
          45.02918048519011
        ],
        [
          2042,
          42.17527319582
        ],
        [
          2043,
          43.484839797341195
        ],
        [
          2044,
          43.642869329413486
        ],
        [
          2045,
          42.09487916263538
        ],
        [
          2046,
          40.80232756788317
        ],
        [
          2047,
          40.15884659664006
        ],
        [
          2048,
          40.242469845074204
        ],
        [
          2049,
          39.293213216039305
        ],
        [
          2050,
          39.5368623862927
        ],
        [
          2051,
          39.86586091068611
        ]
      ]
    },
    {
      "seriesName": "SEAI_COAL",
      "seriesValues": [
        [
          2018,
          18.102337256817947
        ],
        [
          2019,
          12.058389725777385
        ],
        [
          2020,
          11.89721132809705
        ],
        [
          2021,
          12.224032920165675
        ],
        [
          2022,
          8.92285451119252
        ],
        [
          2023,
          5.49871227430927
        ],
        [
          2024,
          3.8531062266750253
        ],
        [
          2025,
          3.850575162216235
        ],
        [
          2026,
          3.8480694102027737
        ],
        [
          2027,
          3.8455887158248667
        ],
        [
          2028,
          3.8431328284702975
        ],
        [
          2029,
          3.840701500025132
        ],
        [
          2030,
          3.838294484896907
        ],
        [
          2031,
          3.8359115399642576
        ],
        [
          2032,
          3.8335524244246058
        ],
        [
          2033,
          3.8312168999771967
        ],
        [
          2034,
          3.8289047306353465
        ],
        [
          2035,
          3.8266156826229127
        ],
        [
          2036,
          3.8243495248311663
        ],
        [
          2037,
          3.82210602818466
        ],
        [
          2038,
          3.8198849638461048
        ],
        [
          2039,
          3.8176861061155307
        ],
        [
          2040,
          3.6000003870851853
        ],
        [
          2041,
          3.3637400738500847
        ],
        [
          2042,
          2.9990263709669343
        ],
        [
          2043,
          2.634312668066282
        ],
        [
          2044,
          2.634312642152698
        ],
        [
          2045,
          2.6343125995938617
        ],
        [
          2046,
          2.6343125637681033
        ],
        [
          2047,
          2.6343125468046766
        ],
        [
          2048,
          2.634312527448971
        ],
        [
          2049,
          2.634312476078879
        ],
        [
          2050,
          2.6343124638013777
        ],
        [
          2051,
          2.6343124644595
        ]
      ]
    },
    {
      "seriesName": "SEAI_ELECTRICITY",
      "seriesValues": [
        [
          2018,
          99.83832034539024
        ],
        [
          2019,
          102.28193041393156
        ],
        [
          2020,
          102.88636111363618
        ],
        [
          2021,
          108.51357929887703
        ],
        [
          2022,
          116.83882120262852
        ],
        [
          2023,
          115.89168503965406
        ],
        [
          2024,
          123.58908947650431
        ],
        [
          2025,
          132.706425789237
        ],
        [
          2026,
          144.38034493097578
        ],
        [
          2027,
          150.20390031354984
        ],
        [
          2028,
          156.80877819596756
        ],
        [
          2029,
          167.3840387991953
        ],
        [
          2030,
          195.28281120908508
        ],
        [
          2031,
          202.6884120229142
        ],
        [
          2032,
          207.09759277760386
        ],
        [
          2033,
          213.56376310060818
        ],
        [
          2034,
          222.66953282610734
        ],
        [
          2035,
          235.67414803612655
        ],
        [
          2036,
          244.6702322019278
        ],
        [
          2037,
          252.62887064864262
        ],
        [
          2038,
          258.46387839691477
        ],
        [
          2039,
          266.2548071511704
        ],
        [
          2040,
          272.4521821693542
        ],
        [
          2041,
          278.6985728544508
        ],
        [
          2042,
          284.1181055075584
        ],
        [
          2043,
          287.624671023695
        ],
        [
          2044,
          290.45258189997475
        ],
        [
          2045,
          292.6058106417776
        ],
        [
          2046,
          294.3045318431543
        ],
        [
          2047,
          296.2480688306111
        ],
        [
          2048,
          297.2814330858191
        ],
        [
          2049,
          300.35043872760264
        ],
        [
          2050,
          302.80569220435444
        ],
        [
          2051,
          305.572868745187
        ]
      ]
    },
    {
      "seriesName": "SEAI_NATGAS",
      "seriesValues": [
        [
          2018,
          81.37344664558081
        ],
        [
          2019,
          80.25873119004764
        ],
        [
          2020,
          87.6293936751063
        ],
        [
          2021,
          88.87862439280875
        ],
        [
          2022,
          83.70600002614262
        ],
        [
          2023,
          96.13466461171991
        ],
        [
          2024,
          91.55178858499069
        ],
        [
          2025,
          93.07114666917667
        ],
        [
          2026,
          89.53134059586272
        ],
        [
          2027,
          83.17854004313055
        ],
        [
          2028,
          79.73601980693492
        ],
        [
          2029,
          80.75733837444727
        ],
        [
          2030,
          69.14474301514616
        ],
        [
          2031,
          67.1626804560944
        ],
        [
          2032,
          69.99191811966854
        ],
        [
          2033,
          68.01472232868171
        ],
        [
          2034,
          67.14651845441409
        ],
        [
          2035,
          64.73337661651654
        ],
        [
          2036,
          59.2327360932938
        ],
        [
          2037,
          51.50190373226386
        ],
        [
          2038,
          44.91728359713294
        ],
        [
          2039,
          34.38508710067469
        ],
        [
          2040,
          26.058146650237134
        ],
        [
          2041,
          21.25774766207559
        ],
        [
          2042,
          17.703653962269325
        ],
        [
          2043,
          14.58784149641668
        ],
        [
          2044,
          11.733799262912598
        ],
        [
          2045,
          9.896178492035169
        ],
        [
          2046,
          8.739881436864877
        ],
        [
          2047,
          8.461143375803218
        ],
        [
          2048,
          6.939469785527951
        ],
        [
          2049,
          4.314800206877185
        ],
        [
          2050,
          3.9689870744916487
        ],
        [
          2051,
          3.6257451385772517
        ]
      ]
    },
    {
      "seriesName": "SEAI_OIL",
      "seriesValues": [
        [
          2018,
          299.36378345932263
        ],
        [
          2019,
          291.7768449345769
        ],
        [
          2020,
          240.4784117949582
        ],
        [
          2021,
          244.66147187527483
        ],
        [
          2022,
          272.0113861725756
        ],
        [
          2023,
          278.65911359542883
        ],
        [
          2024,
          275.2348495225427
        ],
        [
          2025,
          263.16782118320555
        ],
        [
          2026,
          242.07333404054944
        ],
        [
          2027,
          227.93898046929155
        ],
        [
          2028,
          212.81587539501527
        ],
        [
          2029,
          190.8323959465362
        ],
        [
          2030,
          164.47360790829666
        ],
        [
          2031,
          159.7789587009016
        ],
        [
          2032,
          150.4230836250664
        ],
        [
          2033,
          140.2088451207405
        ],
        [
          2034,
          125.42320901649057
        ],
        [
          2035,
          101.90009074889882
        ],
        [
          2036,
          90.11397559946064
        ],
        [
          2037,
          82.66850532527252
        ],
        [
          2038,
          77.6551933160441
        ],
        [
          2039,
          74.41122050541311
        ],
        [
          2040,
          72.31670391851416
        ],
        [
          2041,
          72.04475969331561
        ],
        [
          2042,
          72.60857311768999
        ],
        [
          2043,
          71.68727336379312
        ],
        [
          2044,
          71.33120162430349
        ],
        [
          2045,
          73.08436384863818
        ],
        [
          2046,
          74.0650054761797
        ],
        [
          2047,
          73.79010252379932
        ],
        [
          2048,
          73.75879944442975
        ],
        [
          2049,
          72.54323752474957
        ],
        [
          2050,
          71.62941528716591
        ],
        [
          2051,
          71.18732279772942
        ]
      ]
    },
    {
      "seriesName": "SEAI_OTHER_RENEWABLES",
      "seriesValues": [
        [
          2018,
          2.5558348961550705
        ],
        [
          2019,
          2.8894154461240853
        ],
        [
          2020,
          2.7942501829157944
        ],
        [
          2021,
          4.698235381113778
        ],
        [
          2022,
          7.705638472907011
        ],
        [
          2023,
          11.248131552614684
        ],
        [
          2024,
          14.93090941007851
        ],
        [
          2025,
          18.259880813696427
        ],
        [
          2026,
          21.912670794988113
        ],
        [
          2027,
          26.033853842905778
        ],
        [
          2028,
          27.828367964173257
        ],
        [
          2029,
          28.98213932852844
        ],
        [
          2030,
          29.09151362437639
        ],
        [
          2031,
          28.910160630853504
        ],
        [
          2032,
          28.814358419104984
        ],
        [
          2033,
          29.194972991936968
        ],
        [
          2034,
          29.435850486656506
        ],
        [
          2035,
          30.798377708783566
        ],
        [
          2036,
          32.186690762325384
        ],
        [
          2037,
          33.962322790588715
        ],
        [
          2038,
          35.33291763623497
        ],
        [
          2039,
          38.394623158457506
        ],
        [
          2040,
          42.09841398505564
        ],
        [
          2041,
          43.07115434061639
        ],
        [
          2042,
          43.511397487173205
        ],
        [
          2043,
          44.176535218623464
        ],
        [
          2044,
          45.19089087580359
        ],
        [
          2045,
          45.9284370177444
        ],
        [
          2046,
          46.6575807735369
        ],
        [
          2047,
          47.269519504961906
        ],
        [
          2048,
          48.018481336689185
        ],
        [
          2049,
          49.411662393971504
        ],
        [
          2050,
          49.59808691262346
        ],
        [
          2051,
          49.69209108527062
        ]
      ]
    },
    {
      "seriesName": "SEAI_PEAT",
      "seriesValues": [
        [
          2018,
          8.27506971116591
        ],
        [
          2019,
          7.854
        ],
        [
          2020,
          7.84
        ],
        [
          2021,
          7.448
        ],
        [
          2022,
          6.732
        ],
        [
          2023,
          0.30216138866901
        ],
        [
          2024,
          0.126494201027763
        ],
        [
          2025,
          0.12522924766944
        ],
        [
          2026,
          0.12397695471927
        ],
        [
          2027,
          0.122737184621618
        ],
        [
          2028,
          0.121509812282645
        ],
        [
          2029,
          0.120294713916943
        ],
        [
          2030,
          0.119091766615325
        ],
        [
          2031,
          0.117900848832046
        ],
        [
          2032,
          0.116721840183892
        ],
        [
          2033,
          0.115554621543754
        ],
        [
          2034,
          0.114399074898805
        ],
        [
          2035,
          0.113255083086753
        ],
        [
          2036,
          0.112122530859789
        ],
        [
          2037,
          0.111001303726283
        ],
        [
          2038,
          0.109891281928296
        ],
        [
          2039,
          0.108792352025677
        ],
        [
          2040,
          0.0
        ],
        [
          2041,
          0.0
        ],
        [
          2042,
          0.0
        ],
        [
          2043,
          0.0
        ],
        [
          2044,
          0.0
        ],
        [
          2045,
          0.0
        ],
        [
          2046,
          0.0
        ],
        [
          2047,
          0.0
        ],
        [
          2048,
          0.0
        ],
        [
          2049,
          0.0
        ],
        [
          2050,
          0.0
        ]
      ]
    },
    {
      "seriesName": "SEAI_HYDROGEN",
      "seriesValues": [
        [
          2021,
          0.0
        ],
        [
          2026,
          0.0
        ],
        [
          2027,
          0.0
        ],
        [
          2028,
          0.0
        ],
        [
          2029,
          0.0
        ],
        [
          2030,
          0.0
        ],
        [
          2031,
          0.0
        ],
        [
          2032,
          0.0
        ],
        [
          2033,
          0.0
        ],
        [
          2034,
          1.0562591057775942e-06
        ],
        [
          2035,
          1.776115211254057e-06
        ],
        [
          2036,
          2.102259640827326e-06
        ],
        [
          2037,
          2.5042249086110943e-06
        ],
        [
          2038,
          3.1550458510172734e-06
        ],
        [
          2039,
          4.5908588483117795e-06
        ],
        [
          2040,
          6.268928866096944e-06
        ],
        [
          2041,
          7.661672674716442e-06
        ],
        [
          2042,
          7.906168141194607e-06
        ],
        [
          2043,
          8.182968374436729e-06
        ],
        [
          2044,
          8.106751978223346e-06
        ],
        [
          2045,
          7.75042782548408e-06
        ],
        [
          2046,
          8.284203334647138e-06
        ],
        [
          2047,
          8.621155763075348e-06
        ],
        [
          2048,
          8.877555395360719e-06
        ],
        [
          2049,
          8.227925343094122e-06
        ],
        [
          2050,
          8.247123681600068e-06
        ],
        [
          2051,
          9.889671166362785e-06
        ]
      ]
    },
    {
      "seriesName": "SEAI_HEAT",
      "seriesValues": [
        [
          2023,
          1.99999999981042
        ],
        [
          2024,
          4.249999999455846
        ],
        [
          2025,
          5.572500039913643
        ],
        [
          2026,
          7.093375036146625
        ],
        [
          2027,
          8.842381292675139
        ],
        [
          2028,
          10.140618729709168
        ],
        [
          2029,
          11.670904297063206
        ],
        [
          2030,
          12.556464594912612
        ],
        [
          2031,
          13.448974199520478
        ],
        [
          2032,
          13.661118441281785
        ],
        [
          2033,
          13.953394368635427
        ],
        [
          2034,
          14.243050033079534
        ],
        [
          2035,
          14.53077982605633
        ],
        [
          2036,
          14.7763061999712
        ],
        [
          2037,
          14.900809612621604
        ],
        [
          2038,
          15.000528185264809
        ],
        [
          2039,
          14.687699479472577
        ],
        [
          2040,
          14.680829693512345
        ],
        [
          2041,
          14.671839164795717
        ],
        [
          2042,
          14.618451892624618
        ],
        [
          2043,
          14.460355079279017
        ],
        [
          2044,
          14.211943875621936
        ],
        [
          2045,
          14.128170767294208
        ],
        [
          2046,
          14.044069063659503
        ],
        [
          2047,
          13.993506041777405
        ],
        [
          2048,
          14.006647366905083
        ],
        [
          2049,
          14.005558785802473
        ],
        [
          2050,
          14.010367060810747
        ],
        [
          2051,
          14.015382835599173
        ]
      ]
    }
  ]
}