{
  "name": "mitigation_cb2024-350mt-led",
  "data": [
    {
      "seriesName": "RSDAHT",
      "seriesValues": [
        [
          2018,
          0.2343978419484867
        ],
        [
          2019,
          0.9612663691846054
        ],
        [
          2020,
          1.8554284490373658
        ],
        [
          2021,
          2.675863686645087
        ],
        [
          2022,
          3.9160644359890058
        ],
        [
          2023,
          5.924521694609671
        ],
        [
          2024,
          7.01081049287134
        ],
        [
          2025,
          8.100995008030232
        ],
        [
          2026,
          9.19507519259068
        ],
        [
          2027,
          10.293051215100782
        ],
        [
          2028,
          11.394923006482228
        ],
        [
          2029,
          12.500690509486763
        ],
        [
          2030,
          13.610353564273684
        ],
        [
          2031,
          14.668184222900415
        ],
        [
          2032,
          15.730923545846327
        ],
        [
          2033,
          16.679112246896942
        ],
        [
          2034,
          17.739201743483456
        ],
        [
          2035,
          18.816677980780685
        ],
        [
          2036,
          19.87878553248366
        ],
        [
          2037,
          21.019317855297945
        ],
        [
          2038,
          22.14117471557593
        ],
        [
          2039,
          23.292062811095317
        ],
        [
          2040,
          23.399226365584255
        ],
        [
          2041,
          23.48879384127394
        ],
        [
          2042,
          23.578720445367694
        ],
        [
          2043,
          23.65472483247284
        ],
        [
          2044,
          23.72993088762753
        ],
        [
          2045,
          23.80433856121205
        ],
        [
          2046,
          23.877947771073526
        ],
        [
          2047,
          23.889781858868638
        ],
        [
          2048,
          23.876758924105406
        ],
        [
          2049,
          23.86266122176345
        ],
        [
          2050,
          23.847662814298847
        ],
        [
          2051,
          23.826298625414275
        ]
      ]
    },
    {
      "seriesName": "RSDAHT2",
      "seriesValues": [
        [
          2018,
          0.2537237751124894
        ],
        [
          2019,
          0.2413517019757819
        ],
        [
          2020,
          0.1223516253653898
        ],
        [
          2021,
          0.1929630182319156
        ],
        [
          2022,
          0.2032435389008168
        ],
        [
          2023,
          0.1905408176160429
        ],
        [
          2024,
          0.17783809643696188
        ],
        [
          2025,
          0.1651353752542639
        ],
        [
          2026,
          0.1524326541271414
        ],
        [
          2027,
          0.1397299329430476
        ],
        [
          2028,
          0.1270272117643474
        ],
        [
          2029,
          0.1143244905816041
        ],
        [
          2030,
          0.1016217694089574
        ],
        [
          2031,
          0.08891904820695891
        ],
        [
          2032,
          0.0762163270181882
        ],
        [
          2033,
          0.0635136058296786
        ],
        [
          2034,
          0.0508108846375261
        ],
        [
          2035,
          0.0381081634517594
        ],
        [
          2036,
          0.0254054422590667
        ],
        [
          2037,
          0.012702721085100172
        ]
      ]
    },
    {
      "seriesName": "RSDCOA",
      "seriesValues": [
        [
          2018,
          4.144308721471034
        ],
        [
          2019,
          4.388666292115495
        ],
        [
          2020,
          3.1717143691802736
        ],
        [
          2021,
          3.249372751286242
        ],
        [
          2022,
          3.6957190324811275
        ],
        [
          2023,
          3.4647365782680435
        ],
        [
          2024,
          3.23375415847915
        ],
        [
          2025,
          3.002771698936745
        ],
        [
          2026,
          2.7717893331796883
        ],
        [
          2027,
          2.5408068461730693
        ],
        [
          2028,
          2.309824408526505
        ],
        [
          2029,
          2.078841969788658
        ],
        [
          2030,
          2.0096493108036944
        ],
        [
          2031,
          2.0871108223451547
        ],
        [
          2032,
          2.272507804091285
        ],
        [
          2033,
          1.4919019284847317
        ],
        [
          2034,
          0.9239298119843866
        ],
        [
          2035,
          0.6929473458477067
        ],
        [
          2036,
          0.46196489587491923
        ],
        [
          2037,
          0.23098243150869813
        ],
        [
          2038,
          4.67044841644727e-08
        ],
        [
          2039,
          3.87756622639325e-08
        ],
        [
          2040,
          3.12213502688575e-08
        ],
        [
          2041,
          3.03112544350799e-08
        ],
        [
          2042,
          2.57947728958579e-08
        ],
        [
          2043,
          2.2410829068028402e-08
        ],
        [
          2044,
          1.01998814783989e-08
        ]
      ]
    },
    {
      "seriesName": "RSDELC",
      "seriesValues": [
        [
          2018,
          1.196904932508997
        ],
        [
          2019,
          1.5280671553928216
        ],
        [
          2020,
          2.6400441658662297
        ],
        [
          2021,
          2.702010107222093
        ],
        [
          2022,
          2.9330187903832274
        ],
        [
          2023,
          5.632198151526469
        ],
        [
          2024,
          6.180514919619097
        ],
        [
          2025,
          6.724972530065385
        ],
        [
          2026,
          7.2656312461622194
        ],
        [
          2027,
          7.802550027905082
        ],
        [
          2028,
          8.335786366732261
        ],
        [
          2029,
          8.865396444293598
        ],
        [
          2030,
          9.391435077886074
        ],
        [
          2031,
          9.87894663222757
        ],
        [
          2032,
          10.36132734098539
        ],
        [
          2033,
          10.77130697395098
        ],
        [
          2034,
          11.2368366151695
        ],
        [
          2035,
          11.704533723730053
        ],
        [
          2036,
          12.156536316634615
        ],
        [
          2037,
          12.643856111975557
        ],
        [
          2038,
          13.115190937835903
        ],
        [
          2039,
          13.628439298943835
        ],
        [
          2040,
          13.505157742560952
        ],
        [
          2041,
          13.399432250370056
        ],
        [
          2042,
          13.293322004394184
        ],
        [
          2043,
          13.201081793881155
        ],
        [
          2044,
          13.109596499658583
        ],
        [
          2045,
          13.018848438278086
        ],
        [
          2046,
          12.92882554941296
        ],
        [
          2047,
          12.8193634659321
        ],
        [
          2048,
          12.702809513496147
        ],
        [
          2049,
          12.587268544606559
        ],
        [
          2050,
          12.47242706911958
        ],
        [
          2051,
          12.358646168943721
        ]
      ]
    },
    {
      "seriesName": "RSDGAS",
      "seriesValues": [
        [
          2018,
          6.72558064199687
        ],
        [
          2019,
          6.664358366994283
        ],
        [
          2020,
          5.381976325364118
        ],
        [
          2021,
          5.155405059760433
        ],
        [
          2022,
          4.0900490460972
        ],
        [
          2023,
          5.186018374909023
        ],
        [
          2024,
          4.92391834392537
        ],
        [
          2025,
          4.6019035089542095
        ],
        [
          2026,
          4.23853596038749
        ],
        [
          2027,
          3.9006067558726896
        ],
        [
          2028,
          3.5662259358045088
        ],
        [
          2029,
          3.3046820876453333
        ],
        [
          2030,
          3.0365939129699933
        ],
        [
          2031,
          2.707704629583397
        ],
        [
          2032,
          2.3708533063683745
        ],
        [
          2033,
          1.8837113853953158
        ],
        [
          2034,
          1.528604561307309
        ],
        [
          2035,
          1.1738763513069717
        ],
        [
          2036,
          0.8267967912949903
        ],
        [
          2037,
          0.5104885099058932
        ],
        [
          2038,
          0.2687353122803952
        ],
        [
          2039,
          8.438804816811143e-07
        ],
        [
          2040,
          6.348455697073115e-07
        ]
      ]
    },
    {
      "seriesName": "RSDKER",
      "seriesValues": [
        [
          2018,
          37.769939558691746
        ],
        [
          2019,
          36.19096986152598
        ],
        [
          2020,
          39.13079833331996
        ],
        [
          2021,
          36.45733659871735
        ],
        [
          2022,
          33.80995512973554
        ],
        [
          2023,
          25.442179887886997
        ],
        [
          2024,
          23.262350160749705
        ],
        [
          2025,
          21.074089820373352
        ],
        [
          2026,
          19.954131611814727
        ],
        [
          2027,
          17.928888603065403
        ],
        [
          2028,
          15.899957744932873
        ],
        [
          2029,
          13.900024279067273
        ],
        [
          2030,
          11.750784752467071
        ],
        [
          2031,
          9.590935603439808
        ],
        [
          2032,
          7.9940476449137305
        ],
        [
          2033,
          6.439905796337127
        ],
        [
          2034,
          4.926770325484582
        ],
        [
          2035,
          3.417957732061639
        ],
        [
          2036,
          1.9014535790453633
        ],
        [
          2037,
          0.42116967386738424
        ],
        [
          2038,
          1.077181361034801e-07
        ],
        [
          2039,
          1.43822859248566e-07
        ],
        [
          2040,
          2.04138601797111e-08
        ],
        [
          2041,
          2.03926621795451e-08
        ],
        [
          2042,
          3.09224243767308e-08
        ],
        [
          2044,
          1.03163827531545e-08
        ],
        [
          2047,
          1.03660191372877e-08
        ],
        [
          2051,
          7.73693628775226e-08
        ]
      ]
    },
    {
      "seriesName": "RSDLPG",
      "seriesValues": [
        [
          2018,
          1.5038115851948959
        ],
        [
          2019,
          1.565282766230254
        ],
        [
          2020,
          1.7737895286817038
        ],
        [
          2021,
          1.5557128250944252
        ],
        [
          2022,
          1.47595965470485
        ],
        [
          2023,
          1.395455087060326
        ],
        [
          2024,
          1.3149504998257437
        ],
        [
          2025,
          1.2344459116058655
        ],
        [
          2026,
          1.1539413304156048
        ],
        [
          2027,
          1.0734367425625704
        ],
        [
          2028,
          0.9929321581843382
        ],
        [
          2029,
          0.9124275720917199
        ],
        [
          2030,
          0.8319229984468673
        ],
        [
          2031,
          0.7514191449788564
        ],
        [
          2032,
          0.6709138225748057
        ],
        [
          2033,
          0.590409229164232
        ],
        [
          2034,
          0.5099046364830078
        ],
        [
          2035,
          0.42940004835091833
        ],
        [
          2036,
          0.3488954556722431
        ],
        [
          2037,
          0.2683908481896812
        ],
        [
          2038,
          6.418641386222828e-07
        ],
        [
          2039,
          6.462242513851081e-07
        ],
        [
          2040,
          5.796562207611711e-07
        ],
        [
          2041,
          5.708319184867848e-07
        ],
        [
          2042,
          5.663812790911157e-07
        ],
        [
          2043,
          5.329900971930583e-07
        ],
        [
          2044,
          5.681877463389521e-07
        ],
        [
          2045,
          5.447383629211474e-07
        ],
        [
          2046,
          5.39038128209488e-07
        ],
        [
          2047,
          5.34579443092455e-07
        ],
        [
          2048,
          3.762451378131532e-07
        ],
        [
          2049,
          2.02772354436411e-08
        ],
        [
          2050,
          1.00650701130239e-08
        ],
        [
          2051,
          3.868876282401245e-07
        ]
      ]
    },
    {
      "seriesName": "RSDPEA",
      "seriesValues": [
        [
          2018,
          5.3546829882649245
        ],
        [
          2019,
          5.524964479117492
        ],
        [
          2020,
          5.62454184879347
        ],
        [
          2021,
          5.283821429845734
        ],
        [
          2022,
          4.333879189446089
        ],
        [
          2023,
          4.672953782888935
        ],
        [
          2024,
          4.7020900393673015
        ],
        [
          2025,
          4.747848025897932
        ],
        [
          2026,
          3.234204341680807
        ],
        [
          2027,
          2.9646873092182786
        ],
        [
          2028,
          2.69517030645514
        ],
        [
          2029,
          2.4256532960699917
        ],
        [
          2030,
          2.156136263446504
        ],
        [
          2031,
          1.8866192461614835
        ],
        [
          2032,
          1.7298770591103103
        ],
        [
          2033,
          1.4415642051232127
        ],
        [
          2034,
          1.1532513528742165
        ],
        [
          2035,
          0.8649384930491273
        ],
        [
          2036,
          0.5766256558423228
        ],
        [
          2037,
          0.2883127884478963
        ],
        [
          2038,
          2.6677967638590198e-08
        ],
        [
          2039,
          2.11203225653181e-08
        ]
      ]
    },
    {
      "seriesName": "RSDSOL",
      "seriesValues": [
        [
          2018,
          0.265030855565222
        ],
        [
          2019,
          0.2527797403399
        ],
        [
          2020,
          0.117971049358781
        ],
        [
          2021,
          0.171080642627624
        ],
        [
          2022,
          0.212867151073394
        ],
        [
          2023,
          0.199562953729507
        ],
        [
          2024,
          0.186258756779061
        ],
        [
          2025,
          0.172954559828699
        ],
        [
          2026,
          0.159650363074662
        ],
        [
          2027,
          0.146346166126956
        ],
        [
          2028,
          0.133041969195036
        ],
        [
          2029,
          0.119737772249508
        ],
        [
          2030,
          0.10643357531948
        ],
        [
          2031,
          0.0931293782984098
        ],
        [
          2032,
          0.0798251813301992
        ],
        [
          2033,
          0.0665209843628892
        ],
        [
          2034,
          0.0532167873818417
        ],
        [
          2035,
          0.0399125904244374
        ],
        [
          2036,
          0.0266083934410431
        ],
        [
          2037,
          0.0133041965280364
        ]
      ]
    },
    {
      "seriesName": "RSDWOO",
      "seriesValues": [
        [
          2018,
          0.9116474360533745
        ],
        [
          2019,
          0.7894350446844385
        ],
        [
          2020,
          0.8098539423340299
        ],
        [
          2021,
          0.8727737807686029
        ],
        [
          2022,
          0.7721093161986967
        ],
        [
          2023,
          1.069167610660183
        ],
        [
          2024,
          1.6234265874934204
        ],
        [
          2025,
          2.166883076725461
        ],
        [
          2026,
          2.591891629964844
        ],
        [
          2027,
          3.128479683004167
        ],
        [
          2028,
          3.670107862551469
        ],
        [
          2029,
          4.197156470980432
        ],
        [
          2030,
          4.816625923089983
        ],
        [
          2031,
          5.414446042626041
        ],
        [
          2032,
          4.949809949587011
        ],
        [
          2033,
          5.451176627618275
        ],
        [
          2034,
          5.739909536837579
        ],
        [
          2035,
          5.691652787612276
        ],
        [
          2036,
          5.643396013444525
        ],
        [
          2037,
          5.595139244652172
        ],
        [
          2038,
          4.307904736128679
        ],
        [
          2039,
          1.4896429084448226
        ],
        [
          2040,
          1.2399211732570508
        ],
        [
          2041,
          0.9897224760461524
        ],
        [
          2042,
          0.7390470796322713
        ],
        [
          2043,
          0.4878951838373015
        ],
        [
          2044,
          0.23626652693900413
        ],
        [
          2045,
          1.0464671206334045e-06
        ],
        [
          2046,
          7.952323304238014e-07
        ],
        [
          2047,
          9.327885843654317e-07
        ],
        [
          2048,
          7.76258689367931e-07
        ],
        [
          2049,
          7.163489183943952e-07
        ],
        [
          2050,
          7.185286993099174e-07
        ],
        [
          2051,
          6.876353350237929e-07
        ]
      ]
    },
    {
      "seriesName": "RSDBDL",
      "seriesValues": [
        [
          2023,
          0.2516758199644457
        ],
        [
          2024,
          0.25167254979273135
        ],
        [
          2025,
          0.2516692796938299
        ],
        [
          2026,
          0.287385699983276
        ],
        [
          2027,
          0.32959516548564366
        ],
        [
          2028,
          0.35949917518410623
        ],
        [
          2029,
          0.35949597531506833
        ],
        [
          2030,
          0.3594929069170039
        ],
        [
          2031,
          0.5287672531449544
        ],
        [
          2032,
          0.6977148292358456
        ],
        [
          2033,
          1.2186550484457053
        ],
        [
          2034,
          1.423566210221676
        ],
        [
          2035,
          1.5915221504343482
        ],
        [
          2036,
          1.8035730663294078
        ],
        [
          2037,
          1.818177798584594
        ],
        [
          2038,
          1.8181746400082037
        ],
        [
          2039,
          1.4587116220578307
        ],
        [
          2040,
          1.4479785538715708
        ],
        [
          2041,
          1.4371652555367485
        ],
        [
          2042,
          1.4262703548318665
        ],
        [
          2043,
          1.4152937841626256
        ],
        [
          2044,
          1.4042355309940624
        ],
        [
          2045,
          1.3843839224331287
        ],
        [
          2046,
          1.234243021174302
        ],
        [
          2047,
          1.1649129770518016
        ],
        [
          2048,
          1.12567919834143
        ],
        [
          2049,
          1.0891437828192598
        ],
        [
          2050,
          1.0506496664553917
        ],
        [
          2051,
          1.04689859926642
        ]
      ]
    },
    {
      "seriesName": "RSDBGS",
      "seriesValues": [
        [
          2023,
          0.13246384138112818
        ],
        [
          2024,
          0.05809471988340757
        ],
        [
          2025,
          0.04364039239831397
        ],
        [
          2026,
          0.07053879269235122
        ],
        [
          2027,
          0.07199883129622577
        ],
        [
          2028,
          0.09496866043165145
        ],
        [
          2029,
          0.10624246712190237
        ],
        [
          2030,
          0.1238930491123982
        ],
        [
          2031,
          0.11631323844240528
        ],
        [
          2032,
          0.11669528753635268
        ],
        [
          2033,
          0.08865672759081249
        ],
        [
          2034,
          0.08871694533876681
        ],
        [
          2035,
          0.10697600194658884
        ],
        [
          2036,
          0.11758640240067152
        ],
        [
          2037,
          0.15234129730074025
        ],
        [
          2038,
          0.1423177553070865
        ],
        [
          2039,
          8.438268905671492e-07
        ],
        [
          2040,
          6.348816758417088e-07
        ],
        [
          2041,
          1.3198245088540475e-06
        ],
        [
          2042,
          1.4470538921535536e-06
        ],
        [
          2043,
          1.5127002221272162e-06
        ],
        [
          2044,
          1.5137710715759655e-06
        ],
        [
          2045,
          1.8738177671929354e-06
        ],
        [
          2046,
          1.7007337219224745e-06
        ],
        [
          2047,
          1.9358864107212405e-06
        ],
        [
          2048,
          0.0024642576872336763
        ],
        [
          2049,
          1.6867704298224284e-06
        ],
        [
          2050,
          1.6080318354496426e-06
        ],
        [
          2051,
          2.0503751223340093e-06
        ]
      ]
    },
    {
      "seriesName": "RSDETH",
      "seriesValues": [
        [
          2023,
          5.64101273467286e-05
        ],
        [
          2024,
          5.26491087719865e-05
        ],
        [
          2025,
          4.88869282039131e-05
        ],
        [
          2026,
          4.51303858732904e-05
        ],
        [
          2027,
          4.13694378163456e-05
        ],
        [
          2028,
          3.76086324548803e-05
        ],
        [
          2029,
          3.38477019869788e-05
        ],
        [
          2030,
          3.00868785443829e-05
        ],
        [
          2031,
          2.63257638395509e-05
        ],
        [
          2032,
          2.25646952763881e-05
        ],
        [
          2033,
          1.8803615240646e-05
        ],
        [
          2034,
          1.5042375503698e-05
        ],
        [
          2035,
          1.12813481002484e-05
        ],
        [
          2036,
          7.51995408614639e-06
        ],
        [
          2037,
          3.7595206268533e-06
        ]
      ]
    },
    {
      "seriesName": "RSDHET",
      "seriesValues": [
        [
          2023,
          0.0007794108933599317
        ],
        [
          2024,
          0.10841628474623011
        ],
        [
          2025,
          0.10067226716118922
        ],
        [
          2026,
          0.09292824663778801
        ],
        [
          2027,
          0.08518422618589616
        ],
        [
          2028,
          0.07744020599632119
        ],
        [
          2029,
          0.06969618494571116
        ],
        [
          2030,
          0.061952164753516704
        ],
        [
          2031,
          0.05420814319921885
        ],
        [
          2032,
          0.046464122391020414
        ],
        [
          2033,
          0.03872010158425037
        ],
        [
          2034,
          0.0309760806541564
        ],
        [
          2035,
          0.02323205988604346
        ],
        [
          2036,
          0.015488038807114827
        ],
        [
          2037,
          0.007744017792830219
        ]
      ]
    }
  ]
}