{
  "name": "mitigation_cb2024-350mt-nobio",
  "data": [
    {
      "seriesName": "PWR-COA",
      "seriesValues": [
        [
          2018,
          2090.3849996307363
        ],
        [
          2019,
          632.213980021439
        ],
        [
          2020,
          836.1539769175893
        ],
        [
          2021,
          2839.181744997664
        ],
        [
          2022,
          2275.9109776189835
        ],
        [
          2023,
          786.0352693769055
        ]
      ]
    },
    {
      "seriesName": "PWR-GAS",
      "seriesValues": [
        [
          2018,
          5930.531439180084
        ],
        [
          2019,
          6147.629710825284
        ],
        [
          2020,
          6300.2523317386185
        ],
        [
          2021,
          5414.433213652072
        ],
        [
          2022,
          6370.5807937647205
        ],
        [
          2023,
          6258.9998503070665
        ],
        [
          2024,
          6258.999832306301
        ],
        [
          2025,
          6258.999856922235
        ],
        [
          2026,
          6258.999949429501
        ],
        [
          2027,
          6072.196821291677
        ],
        [
          2028,
          5632.63165016507
        ],
        [
          2029,
          3529.6385727782226
        ],
        [
          2030,
          1326.117301150727
        ],
        [
          2031,
          53.624804642783374
        ],
        [
          2032,
          35.4404498217251
        ],
        [
          2033,
          29.08663384876663
        ],
        [
          2034,
          36.60347314461074
        ],
        [
          2035,
          21.590804966691493
        ],
        [
          2036,
          7.94403948851096
        ],
        [
          2037,
          5.6831476829438
        ],
        [
          2038,
          47.648310918231886
        ],
        [
          2039,
          22.521818453483043
        ],
        [
          2040,
          33.05986758572399
        ],
        [
          2041,
          6.866438937640921
        ],
        [
          2042,
          3.25845859903077
        ],
        [
          2043,
          2.38575439397894
        ],
        [
          2044,
          2.51371439384331e-06
        ]
      ]
    },
    {
      "seriesName": "PWR-MSW",
      "seriesValues": [
        [
          2018,
          370.799999920858
        ],
        [
          2019,
          361.52999866971555
        ],
        [
          2020,
          380.069998482059
        ],
        [
          2021,
          361.5299981483276
        ],
        [
          2022,
          344.8349982802898
        ],
        [
          2023,
          344.83499837196524
        ],
        [
          2024,
          344.83499817088716
        ],
        [
          2025,
          344.83499770392945
        ],
        [
          2026,
          344.8349974137893
        ],
        [
          2027,
          344.834996958765
        ],
        [
          2028,
          344.8349962643994
        ],
        [
          2029,
          344.83500101747654
        ],
        [
          2030,
          344.8349997830183
        ],
        [
          2031,
          344.8349947983286
        ],
        [
          2032,
          344.8349948022606
        ],
        [
          2033,
          344.8349946815574
        ],
        [
          2034,
          344.8349952140992
        ],
        [
          2035,
          344.8349951910269
        ],
        [
          2036,
          344.83499624664324
        ],
        [
          2037,
          344.83498926620837
        ],
        [
          2038,
          344.8349964820415
        ],
        [
          2039,
          344.834995548517
        ],
        [
          2040,
          344.8349933068141
        ],
        [
          2041,
          344.8349942677492
        ],
        [
          2042,
          344.83500015155914
        ],
        [
          2043,
          344.8350001545007
        ],
        [
          2044,
          344.83500015588885
        ],
        [
          2045,
          344.8350001577797
        ],
        [
          2046,
          344.83500016386614
        ],
        [
          2047,
          344.8350001696972
        ],
        [
          2048,
          344.83500017914724
        ],
        [
          2049,
          344.8350001943012
        ],
        [
          2050,
          344.8350001897262
        ],
        [
          2051,
          344.8350002996172
        ]
      ]
    },
    {
      "seriesName": "PWR-OIL",
      "seriesValues": [
        [
          2018,
          109.84270511053134
        ],
        [
          2019,
          249.5420913220809
        ],
        [
          2020,
          351.28144932922805
        ],
        [
          2021,
          1110.776101336443
        ],
        [
          2022,
          819.877053717448
        ],
        [
          2023,
          111.14998445434009
        ],
        [
          2024,
          74.09997739542142
        ],
        [
          2025,
          0.0011410090969741318
        ]
      ]
    },
    {
      "seriesName": "PWR-PEA",
      "seriesValues": [
        [
          2018,
          2377.651999560309
        ],
        [
          2019,
          2174.5359833046964
        ],
        [
          2020,
          1075.3199809673963
        ],
        [
          2021,
          337.5599871251441
        ],
        [
          2022,
          258.79598124094724
        ]
      ]
    },
    {
      "seriesName": "PWR-GAS-CCS",
      "seriesValues": [
        [
          2038,
          0.0
        ],
        [
          2039,
          0.0
        ],
        [
          2040,
          0.0
        ],
        [
          2041,
          0.0
        ],
        [
          2042,
          0.0
        ],
        [
          2043,
          0.0
        ],
        [
          2044,
          0.0
        ],
        [
          2045,
          0.0
        ],
        [
          2046,
          0.0
        ],
        [
          2047,
          0.0
        ],
        [
          2048,
          0.0
        ],
        [
          2049,
          0.0
        ],
        [
          2050,
          0.0
        ],
        [
          2051,
          0.0
        ]
      ]
    },
    {
      "seriesName": "PWR-BIO-CCS",
      "seriesValues": [
        [
          2043,
          -27.31346291660834
        ],
        [
          2044,
          -193.0978152834577
        ],
        [
          2045,
          -203.25739510306144
        ],
        [
          2046,
          -679.1414839703166
        ],
        [
          2047,
          -1262.5522370288097
        ],
        [
          2048,
          -1312.8101282397047
        ],
        [
          2049,
          -1355.872882743223
        ],
        [
          2050,
          -1353.9897251395123
        ],
        [
          2051,
          -1252.0660858737722
        ]
      ]
    }
  ]
}