{
  "name": "mitigation_cb2024-450mt-wem",
  "data": [
    {
      "seriesName": "SRVELC",
      "seriesValues": [
        [
          2018,
          5.236442790784421
        ],
        [
          2019,
          7.673291162849283
        ],
        [
          2020,
          10.110139534919735
        ],
        [
          2021,
          13.371906976549768
        ],
        [
          2022,
          17.588093018970334
        ],
        [
          2023,
          20.49382697646727
        ],
        [
          2024,
          23.399560930024286
        ],
        [
          2025,
          26.30529488337131
        ],
        [
          2026,
          29.211028836776222
        ],
        [
          2027,
          32.1167627902168
        ],
        [
          2028,
          35.022496743692116
        ],
        [
          2029,
          37.92823069715529
        ],
        [
          2030,
          40.83396465058368
        ],
        [
          2031,
          43.739698603985865
        ],
        [
          2032,
          43.73969860411919
        ],
        [
          2033,
          43.73969871444772
        ],
        [
          2034,
          43.739698521221285
        ],
        [
          2035,
          43.73969860304752
        ],
        [
          2036,
          43.73969860174613
        ],
        [
          2037,
          43.73969865935327
        ],
        [
          2038,
          43.73969859999906
        ],
        [
          2039,
          43.73969862560671
        ],
        [
          2040,
          43.73969860676111
        ],
        [
          2041,
          43.739698632381774
        ],
        [
          2042,
          43.73969860293703
        ],
        [
          2043,
          43.73969860399834
        ],
        [
          2044,
          43.739698619006056
        ],
        [
          2045,
          43.73969859454347
        ],
        [
          2046,
          43.73969860376626
        ],
        [
          2047,
          43.73969859948474
        ],
        [
          2048,
          43.73969859651615
        ],
        [
          2049,
          43.73969860722223
        ],
        [
          2050,
          43.73969860416419
        ],
        [
          2051,
          43.739698604322804
        ]
      ]
    },
    {
      "seriesName": "SRVELC-DC-C",
      "seriesValues": [
        [
          2018,
          0.42636248948866023
        ],
        [
          2019,
          0.6247759506742686
        ],
        [
          2020,
          0.8231894118603329
        ],
        [
          2021,
          1.0887695665779435
        ],
        [
          2022,
          1.4320605465457588
        ],
        [
          2023,
          1.668651685494215
        ],
        [
          2024,
          1.9052428241218797
        ],
        [
          2025,
          2.141833962732445
        ],
        [
          2026,
          2.378425101347721
        ],
        [
          2027,
          2.615016239965902
        ],
        [
          2028,
          2.8516073785869134
        ],
        [
          2029,
          3.0881985172069317
        ],
        [
          2030,
          3.3247896558241257
        ],
        [
          2031,
          3.561380794439179
        ],
        [
          2032,
          3.561380794450033
        ],
        [
          2033,
          3.5613808034332197
        ],
        [
          2034,
          3.5613807877003087
        ],
        [
          2035,
          3.561380794362776
        ],
        [
          2036,
          3.561380794256812
        ],
        [
          2037,
          3.5613807989473103
        ],
        [
          2038,
          3.561380794114565
        ],
        [
          2039,
          3.561380796199592
        ],
        [
          2040,
          3.5613807946651463
        ],
        [
          2041,
          3.561380796751233
        ],
        [
          2042,
          3.5613807943537785
        ],
        [
          2043,
          3.561380794440195
        ],
        [
          2044,
          3.5613807956621555
        ],
        [
          2045,
          3.5613807936703537
        ],
        [
          2046,
          3.561380794421295
        ],
        [
          2047,
          3.561380794072687
        ],
        [
          2048,
          3.5613807938309785
        ],
        [
          2049,
          3.5613807947026905
        ],
        [
          2050,
          3.561380794453698
        ],
        [
          2051,
          3.5613807944666123
        ]
      ]
    }
  ]
}