{
  "name": "bau-wam",
  "data": [
    {
      "seriesName": "INDCOA",
      "seriesValues": [
        [
          2018,
          0.0061193008195497
        ],
        [
          2019,
          0.0029323949687147
        ],
        [
          2020,
          0.0055868689110581
        ],
        [
          2021,
          0.0053405776836361
        ],
        [
          2022,
          0.0050938647009764
        ],
        [
          2023,
          0.0024474150249275
        ],
        [
          2024,
          0.0023252926510544
        ],
        [
          2025,
          0.0022031487352104
        ],
        [
          2026,
          0.0020810875645963
        ],
        [
          2027,
          0.0019592281870001
        ],
        [
          2028,
          0.0018372008860541
        ],
        [
          2029,
          0.0017153001753025
        ],
        [
          2030,
          0.0015934076502217998
        ],
        [
          2031,
          0.0014720926686592
        ],
        [
          2032,
          0.001352982545243
        ],
        [
          2033,
          0.0013162651440121
        ],
        [
          2034,
          0.0022029456353687
        ],
        [
          2035,
          0.0019581815167435002
        ],
        [
          2036,
          0.0017134657798637
        ],
        [
          2037,
          0.0014687616784549
        ],
        [
          2038,
          0.0012240751244507
        ],
        [
          2039,
          0.0009794166935646
        ],
        [
          2040,
          0.0007346886565059
        ],
        [
          2041,
          0.0004899367436603001
        ],
        [
          2042,
          0.0002453688827014666
        ],
        [
          2043,
          0.0
        ],
        [
          2044,
          0.0
        ],
        [
          2045,
          0.0
        ],
        [
          2046,
          0.0
        ],
        [
          2047,
          0.0
        ],
        [
          2048,
          0.0
        ],
        [
          2049,
          0.0
        ],
        [
          2050,
          0.0
        ],
        [
          2051,
          0.0
        ]
      ]
    },
    {
      "seriesName": "INDGAS",
      "seriesValues": [
        [
          2018,
          14.970611092578778
        ],
        [
          2019,
          14.371786641586247
        ],
        [
          2020,
          14.62291475035589
        ],
        [
          2021,
          13.47911456248759
        ],
        [
          2022,
          12.882141802071418
        ],
        [
          2023,
          13.421866980989039
        ],
        [
          2024,
          11.6657389881235
        ],
        [
          2025,
          15.440221768060097
        ],
        [
          2026,
          14.86975493238149
        ],
        [
          2027,
          14.467994310669914
        ],
        [
          2028,
          14.014982396613904
        ],
        [
          2029,
          12.760147920819794
        ],
        [
          2030,
          12.426822843320245
        ],
        [
          2031,
          12.147267026466306
        ],
        [
          2032,
          11.92989550732818
        ],
        [
          2033,
          11.714347721680667
        ],
        [
          2034,
          11.357894073158725
        ],
        [
          2035,
          10.967869066353934
        ],
        [
          2036,
          10.571863624001026
        ],
        [
          2037,
          10.172909091428082
        ],
        [
          2038,
          9.772592215463835
        ],
        [
          2039,
          9.371661213258454
        ],
        [
          2040,
          14.623303277812978
        ],
        [
          2041,
          14.317810186656613
        ],
        [
          2042,
          14.052879227957622
        ],
        [
          2043,
          13.777508047933761
        ],
        [
          2044,
          13.67242252407683
        ],
        [
          2045,
          13.335026594916801
        ],
        [
          2046,
          13.243331985829265
        ],
        [
          2047,
          13.244456917232615
        ],
        [
          2048,
          12.978520021644695
        ],
        [
          2049,
          12.604613740021852
        ],
        [
          2050,
          11.93016700372288
        ],
        [
          2051,
          11.662531296313244
        ]
      ]
    },
    {
      "seriesName": "INDOIL",
      "seriesValues": [
        [
          2018,
          0.471329857637403
        ],
        [
          2019,
          0.4524766617357125
        ],
        [
          2020,
          0.4336234668496455
        ],
        [
          2021,
          0.4147702722792316
        ],
        [
          2022,
          0.39591709139287856
        ],
        [
          2023,
          0.3770638953173616
        ],
        [
          2024,
          0.358210699350421
        ],
        [
          2025,
          0.3393575034115461
        ],
        [
          2026,
          0.320504307501307
        ],
        [
          2027,
          0.3016511116227636
        ],
        [
          2028,
          0.28279791578474267
        ],
        [
          2029,
          0.2639447199908142
        ],
        [
          2030,
          0.245091524255972
        ],
        [
          2031,
          0.2262383285917234
        ],
        [
          2032,
          0.2073851330144509
        ],
        [
          2033,
          0.188531937528532
        ],
        [
          2034,
          0.1696787421520342
        ],
        [
          2035,
          0.1508255469100738
        ],
        [
          2036,
          0.1319723518377418
        ],
        [
          2037,
          0.1131191569787901
        ],
        [
          2038,
          0.0942659623915333
        ],
        [
          2039,
          0.0754127681620381
        ],
        [
          2040,
          0.0565595744040831
        ],
        [
          2041,
          0.0377063814905228
        ],
        [
          2042,
          0.0188531900142607
        ],
        [
          2050,
          0.0
        ],
        [
          2051,
          0.0
        ]
      ]
    },
    {
      "seriesName": "INDCOK",
      "seriesValues": [
        [
          2019,
          0.0029421335399504997
        ],
        [
          2020,
          4.2886844006236e-05
        ],
        [
          2021,
          4.44052185266958e-05
        ],
        [
          2022,
          4.63453487690072e-05
        ],
        [
          2023,
          0.002448022439922
        ],
        [
          2024,
          0.0023253720660471
        ],
        [
          2025,
          0.0022027432498345
        ],
        [
          2026,
          0.0020800317052953998
        ],
        [
          2027,
          0.0019571183875288
        ],
        [
          2028,
          0.0018343730257621
        ],
        [
          2029,
          0.0017115011140827999
        ],
        [
          2030,
          0.0015886210849847
        ],
        [
          2031,
          0.0014651636267795
        ],
        [
          2032,
          0.0013395015458491
        ],
        [
          2033,
          0.0011314473267121
        ]
      ]
    },
    {
      "seriesName": "INDBGS",
      "seriesValues": [
        [
          2020,
          0.023370988581397113
        ],
        [
          2022,
          0.3599995241006695
        ]
      ]
    },
    {
      "seriesName": "INDELC",
      "seriesValues": [
        [
          2021,
          0.2137048655478246
        ],
        [
          2022,
          0.4107187670494296
        ],
        [
          2023,
          0.1493644758609943
        ]
      ]
    },
    {
      "seriesName": "INDBIO",
      "seriesValues": [
        [
          2022,
          0.522367429857602
        ],
        [
          2026,
          0.0
        ],
        [
          2027,
          0.0474392237593101
        ],
        [
          2028,
          0.15773397851592752
        ],
        [
          2029,
          0.5148764253735256
        ],
        [
          2030,
          0.7102356504058477
        ],
        [
          2031,
          0.8504528336945905
        ],
        [
          2032,
          0.927111073379697
        ],
        [
          2033,
          1.0005697437431464
        ],
        [
          2034,
          1.2135580293571406
        ],
        [
          2035,
          1.4587417777285803
        ],
        [
          2036,
          1.7075415455311829
        ],
        [
          2037,
          1.957971876104955
        ],
        [
          2038,
          2.2084504099691804
        ],
        [
          2039,
          2.4582340399392684
        ],
        [
          2040,
          2.6106133633468556
        ],
        [
          2041,
          2.762359788797296
        ],
        [
          2042,
          2.87225484053232
        ],
        [
          2043,
          2.991309548826437
        ],
        [
          2044,
          2.9825698306045663
        ],
        [
          2045,
          3.2048781546723735
        ],
        [
          2046,
          3.180233469083433
        ],
        [
          2047,
          3.061528479728378
        ],
        [
          2048,
          3.2086561098679076
        ],
        [
          2049,
          3.462536081472262
        ],
        [
          2050,
          4.015752858198103
        ],
        [
          2051,
          4.283388796405024
        ]
      ]
    },
    {
      "seriesName": "INDH2L",
      "seriesValues": [
        [
          2034,
          0.0
        ],
        [
          2035,
          0.0
        ],
        [
          2036,
          0.0
        ],
        [
          2037,
          0.0
        ],
        [
          2038,
          0.0
        ],
        [
          2039,
          0.0
        ],
        [
          2040,
          0.0
        ],
        [
          2041,
          0.0
        ],
        [
          2042,
          0.0
        ],
        [
          2043,
          0.0
        ],
        [
          2044,
          0.0
        ],
        [
          2045,
          0.0
        ],
        [
          2046,
          0.0
        ],
        [
          2047,
          0.0
        ],
        [
          2048,
          0.0
        ],
        [
          2049,
          0.0
        ],
        [
          2050,
          0.0
        ],
        [
          2051,
          0.0
        ]
      ]
    },
    {
      "seriesName": "INDWOO",
      "seriesValues": [
        [
          2037,
          0.0
        ],
        [
          2038,
          0.0
        ],
        [
          2039,
          0.0
        ],
        [
          2040,
          0.0
        ],
        [
          2041,
          0.0
        ],
        [
          2042,
          0.0
        ],
        [
          2043,
          0.0
        ],
        [
          2045,
          0.0
        ],
        [
          2046,
          0.0
        ],
        [
          2049,
          0.0
        ],
        [
          2050,
          0.0
        ],
        [
          2051,
          0.0
        ]
      ]
    }
  ]
}